my_util_lib/__init__.py
my_util_lib/utils.py
my_util_lib-1.0.6.dist-info/LICENSE.txt
my_util_lib-1.0.6.dist-info/METADATA
my_util_lib-1.0.6.dist-info/WHEEL
my_util_lib-1.0.6.dist-info/top_level.txt
my_util_lib-1.0.6.dist-info/RECORD
