Metadata-Version: 2.1
Name: my-util-lib
Version: 1.0.6
Summary: My util library in Python
Home-page: http://localhost
Author: Me
Author-email: me@test.com
License: MIT
Platform: UNKNOWN
License-File: LICENSE.txt
Requires-Dist: numpy (>=1.19)
